{
  "Changes": [
    {
      "Action": "Load",
      "Target": "Characters/{{Sai}}, Portraits/{{Sai}}",
      "FromFile": "Assets/NPCS/{{TargetPathOnly}}/{{TargetWithoutPath}}.png"
    },
    {
      "Action": "EditData",
      "Target": "Data/Characters",
      "Entries": {
        "{{Sai}}": {
          "DisplayName": "{{i18n:Sai}}",
          "BirthSeason": "Fall",
          "BirthDay": 4,
          "HomeRegion": "Other",
          "Language": "Default",
          "Gender": "Undefined",
          "Age": "Adult",
          "Manner": "Rude",
          "SocialAnxiety": "Shy",
          "Optimism": "Negative",
          "IsDarkSkinned": true,
          "CanBeRomanced": true,
          "LoveInterest": null,
          "Calendar": "HiddenUntilMet",
          "SocialTab": "HiddenUntilMet",
          "CanSocialize": null,
          "CanReceiveGifts": true,
          "CanGreetNearbyCharacters": true,
          "CanCommentOnPurchasedShopItems": null,
          "CanVisitIsland": null,
          "IntroductionsQuest": false,
          "ItemDeliveryQuests": null,
          "PerfectionScore": false,
          "EndSlideShow": "TrailingGroup",
          "SpouseAdopts": null,
          "SpouseWantsChildren": true,
          "SpouseGiftJealousy": null,
          "SpouseGiftJealousyFriendshipChange": -30,
          "SpouseRoom": {
            "MapAsset": null,
            "MapSourceRect": {
              "X": 0,
              "Y": 0,
              "Width": 6,
              "Height": 9
            }
          },
          "SpousePatio": {
            "MapAsset": null,
            "MapSourceRect": {
              "X": 0,
              "Y": 0,
              "Width": 4,
              "Height": 4
            },
            "SpriteAnimationFrames": [
              [ 16, 1500 ]
            ],
            "SpriteAnimationPixelOffset": {
              "X": 0,
              "Y": 0
            }
          },
          "SpouseFloors": [],
          "SpouseWallpapers": [],
          "DumpsterDiveFriendshipEffect": -5,
          "DumpsterDiveEmote": null,
          "FriendsAndFamily": {
          },
          "FlowerDanceCanDance": null,
          "WinterStarGifts": [],
          "WinterStarParticipant": null,
          "UnlockConditions": "PLAYER_HAS_SEEN_EVENT Current ",
          "SpawnIfMissing": true,
          "Home": [
            {
              "Id": "Default",
              "Condition": null,
              "Location": null,
              "Tile": {
                "X": 26,
                "Y": 19
              },
              "Direction": "right"
            }
          ],
          "TextureName": null,
          "Appearance": null,
          "MugShotSourceRect": null,
          "Size": {
            "X": 16,
            "Y": 32
          },
          "Breather": true,
          "BreathChestRect": null,
          "BreathChestPosition": null,
          "Shadow": null,
          "EmoteOffset": {
            "X": 0,
            "Y": 0
          },
          "ShakePortraits": [ 15 ],
          "KissSpriteIndex": 39,
          "KissSpriteFacingRight": false,
          "HiddenProfileEmoteSound": "newRecipe",
          "HiddenProfileEmoteDuration": 4000,
          "HiddenProfileEmoteStartFrame": 32,
          "HiddenProfileEmoteFrameCount": 2,
          "HiddenProfileEmoteFrameDuration": 200.0,
          "FormerCharacterNames": [],
          "CustomFields": null
        }
      }
    },
    //////////////////////////////////////////////////////////////////////////////////////////////////
    {
      "Action": "EditData",
      "Target": "Data/NPCGiftTastes",
      "Entries": {
        "{{Sai}}": "{{i18n:Gifts.Loved}}//{{i18n:Gifts.Liked}}//{{i18n:Gifts.Disliked}}//{{i18n:Gifts.Hated}}//{{i18n:Gifts.Neutral}}//"
      }
    },
    //////////////////////////////////////////////////////////////////////////////////////////////////
    {
      "Action": "EditData",
      "Target": "Data/ConcessionTastes",
      "Entries": {
        "{{Sai}}": {
          "Name": "{{Sai}}",
          "LovedTags": [
            "Apple Slices"
          ],
          "LikedTags": [
            "Truffle Popcorn"
          ],
          "DislikedTags": [
            "Black Licorice"
          ]
        }
      }
    },
    //////////////////////////////////////////////////////////////////////////////////////////////////
    {
      "Action": "EditData",
      "Target": "Strings/StringsFromCSFiles",
      "Entries": {
        "{{Sai}}_Engaged": "{{i18n:Sai}}", //proposal
        "{{Sai}}_AfterWedding": "{{i18n:Sai}}"
      }
    },
    //////////////////////////////////////////////////////////////////////////////////////////////////
    {
      "LogName": "Edel's' Schedule",
      "Action": "EditData",
      "Target": "Characters/schedules/{{Sai}}",
      "Entries": {
        "spring": "",
        "marriage_Mon": "",
        "marriage_Tue": "",
        "marriage_Wed": ""
      }
    },
    //////////////////////////////////////////////////////////////////////////////////////////////////
    {
      "Action": "EditData",
      "Target": "Characters/Dialogue/{{Sai}}",
      "Entries": {
        "breakUp": "{{i18n:Sai.breakUp}}",
        "divorced": "{{i18n:Sai.divorced}}",
        "DumpsterDiveComment": "{{i18n:Sai.DumpsterDiveComment}}",
        "HitBySlingshot": "{{i18n:Sai.HitBySlingshot}}",
        "Resort": "{{i18n:Sai.Resort}}",
        "Resort_Bar": "{{i18n:Sai.Resort_Bar}}",
        "Resort_Chair": "{{i18n:Sai.Resort_Chair}}",
        "Resort_Dance": "{{i18n:Sai.Resort_Dance}}",
        "Resort_Entering": "{{i18n:Sai.Resort_Entering}}",
        "Resort_Leaving": "{{i18n:Sai.Resort_Leaving}}",
        "Resort_Shore": "{{i18n:Sai.Resort_Shore}}",
        "Resort_Towel": "{{i18n:Sai.Resort_Towel}}",
        "Resort_Umbrella": "{{i18n:Sai.Resort_Umbrella}}",
        "Resort_Wander": "{{i18n:Sai.Resort_Wander}}",
        "SpouseFarmhouseClutter": "{{i18n:Sai.SpouseFarmhouseClutter}}",
        "SpouseGiftJealous": "{{i18n:Sai.SpouseGiftJealous}}",
        "Spouse_MonstersInHouse": "{{i18n:Sai.Spouse_MonstersInHouse}}",
        "SpouseStardrop": "{{i18n:Sai.SpouseStardrop}}",
        "WipedMemory": "{{i18n:Sai.WipedMemory}}",
        "AcceptBirthdayGift_Negative": "{{i18n:Sai.AcceptBirthdayGift_Negative}}",
        "AcceptBirthdayGift_Positive": "{{i18n:Sai.AcceptBirthdayGift_Positive}}",
        "AcceptBirthdayGift": "{{i18n:Sai.AcceptBirthdayGift}}",
        "AcceptBouquet": "{{i18n:Sai.AcceptBouquet}}",
        "MovieInvitation": "{{i18n:Sai.MovieInvitation}}",
        "RejectBouquet": "{{i18n:Sai.RejectBouquet}}",
        "RejectGift_Divorced": "{{i18n:Sai.RejectGift_Divorced}}",
        "RejectMermaidPendant": "{{i18n:Sai.RejectMermaidPendant}}",
        "RejectMovieTicket": "{{i18n:Sai.RejectMovieTicket}}",
        "GreenRain": "{{i18n:Sai.GreenRain}}",
        "GreenRainFinished": "{{i18n:Sai.GreenRainFinished}}",

        "Mon": "{{i18n:Sai.Mon_{{Random:{{Range: 0, 3}}}}}}",
        "Tue": "{{i18n:Sai.Tue_{{Random:{{Range: 0, 3}}}}}}",
        "Wed": "{{i18n:Sai.Wed_{{Random:{{Range: 0, 3}}}}}}",
        "Thu": "{{i18n:Sai.Thu_{{Random:{{Range: 0, 3}}}}}}",
        "Fri": "{{i18n:Sai.Fri_{{Random:{{Range: 0, 3}}}}}}",
        "Sat": "{{i18n:Sai.Sat_{{Random:{{Range: 0, 3}}}}}}",
        "Sun": "{{i18n:Sai.Sun_{{Random:{{Range: 0, 3}}}}}}"
      }
    },
    //////////////////////////////////////////////////////////////////////////////////////////////////
    {
      "LogName": "Engaged Dialogue",
      "Action": "EditData",
      "Target": "data/EngagementDialogue",
      "Entries": {
        "{{Sai}}0": "{{i18n:Sai}}",
        "{{Sai}}1": "{{i18n:Sai}}"
      }
    },
    {
      "LogName": "Marriage Dialogue - Base",
      "Action": "EditData",
      "Target": "Characters/Dialogue/MarriageDialogue{{Sai}}",
      "Entries": {
      }
    },
    //////////////////////////////////////////////////////////////////////////////////////////////////
    { //edelintro
      "LogName": "Heart Event - 0",
      "Action": "EditData",
      "Target": "data/events/",
      "Entries": {
      }
    }
  ]
}